techmax_energiez_pkg/__init__.py
techmax_energiez_pkg/server_status.py
techmax_energiez_pkg/validations.py
techmax_energiez_x23176458-0.1.4.dist-info/METADATA
techmax_energiez_x23176458-0.1.4.dist-info/WHEEL
techmax_energiez_x23176458-0.1.4.dist-info/top_level.txt
techmax_energiez_x23176458-0.1.4.dist-info/RECORD
