Metadata-Version: 2.1
Name: techmax_energiez_x23176458
Version: 0.1.4
Summary: Package for validations, techmax project
Home-page: https://github.com/anilgovind-nci/techmax-energiez-package
Author: AnilgovindKA
Author-email: anilgovindk@gmail.com
Classifier: Programming Language :: Python :: 3
Classifier: License :: OSI Approved :: MIT License
Classifier: Operating System :: OS Independent
Requires-Python: >=3.6
